odoo/addons/l10n_it_fatturapa_out_fd/README.rst
odoo/addons/l10n_it_fatturapa_out_fd/__init__.py
odoo/addons/l10n_it_fatturapa_out_fd/__manifest__.py
odoo/addons/l10n_it_fatturapa_out_fd/i18n/it.po
odoo/addons/l10n_it_fatturapa_out_fd/i18n/l10n_it_fatturapa_out_fd.pot
odoo/addons/l10n_it_fatturapa_out_fd/readme/CONTRIBUTORS.rst
odoo/addons/l10n_it_fatturapa_out_fd/readme/DESCRIPTION.rst
odoo/addons/l10n_it_fatturapa_out_fd/static/description/icon.png
odoo/addons/l10n_it_fatturapa_out_fd/static/description/index.html
odoo/addons/l10n_it_fatturapa_out_fd/tests/__init__.py
odoo/addons/l10n_it_fatturapa_out_fd/tests/test_xml_generation.py
odoo/addons/l10n_it_fatturapa_out_fd/tests/data/IT06363391001_00001.xml
odoo/addons/l10n_it_fatturapa_out_fd/wizards/__init__.py
odoo/addons/l10n_it_fatturapa_out_fd/wizards/wizard_export_fatturapa.py
odoo12_addon_l10n_it_fatturapa_out_fd-12.0.1.0.0.99.dev4.dist-info/METADATA
odoo12_addon_l10n_it_fatturapa_out_fd-12.0.1.0.0.99.dev4.dist-info/WHEEL
odoo12_addon_l10n_it_fatturapa_out_fd-12.0.1.0.0.99.dev4.dist-info/top_level.txt
odoo12_addon_l10n_it_fatturapa_out_fd-12.0.1.0.0.99.dev4.dist-info/RECORD
